OptionTest/test.py
Hamza_Option_Test-1.0.0.dist-info/LICENSE.txt
Hamza_Option_Test-1.0.0.dist-info/METADATA
Hamza_Option_Test-1.0.0.dist-info/WHEEL
Hamza_Option_Test-1.0.0.dist-info/top_level.txt
Hamza_Option_Test-1.0.0.dist-info/RECORD
