Metadata-Version: 2.1
Name: Hamza-Option-Test
Version: 1.0.0
Summary: Test pthon package
License-File: LICENSE.txt
